josso/__init__.py
josso/backend.py
josso/wsdl/SSOIdentityManager.xml
josso/wsdl/SSOIdentityProvider.xml
python_josso_auth-0.1.4.dist-info/METADATA
python_josso_auth-0.1.4.dist-info/RECORD
python_josso_auth-0.1.4.dist-info/WHEEL
python_josso_auth-0.1.4.dist-info/top_level.txt
