Metadata-Version: 2.1
Name: python-josso-auth
Version: 0.1.4
Summary: A JOSSO backend for python-social-auth
Home-page: https://github.com/consbio/python-josso-auth
Author: UNKNOWN
Author-email: UNKNOWN
License: BSD
Keywords: python-social-auth,social-auth-app-django,sso,josso
Platform: UNKNOWN
Requires-Dist: social-auth-app-django
Requires-Dist: suds-jurko
Requires-Dist: six
